trapify/__init__.py
trapify-0.1.2.dist-info/DESCRIPTION.rst
trapify-0.1.2.dist-info/entry_points.txt
trapify-0.1.2.dist-info/METADATA
trapify-0.1.2.dist-info/metadata.json
trapify-0.1.2.dist-info/pbr.json
trapify-0.1.2.dist-info/RECORD
trapify-0.1.2.dist-info/top_level.txt
trapify-0.1.2.dist-info/WHEEL
