Metadata-Version: 2.0
Name: trapify
Version: 0.1.2
Summary: KЄЄⱣ ΫØṲЯ ϾØMM∆ИƉ ⱢỊИЄ ₮ЯỊⱢⱢ
Home-page: https://github.com/Miserlou/Trapify
Author: Rich Jones
Author-email: rich@openwatch.net
License: MIT License
Platform: UNKNOWN
Classifier: Environment :: Console
Classifier: License :: OSI Approved :: Apache Software License
Classifier: Operating System :: OS Independent
Classifier: Programming Language :: Python
Classifier: Programming Language :: Python :: 2.6
Classifier: Programming Language :: Python :: 2.7
Classifier: Programming Language :: Python :: 3.0
Classifier: Programming Language :: Python :: 3.1
Classifier: Programming Language :: Python :: 3.2
Classifier: Programming Language :: Python :: 3.3
Classifier: Programming Language :: Python :: 3.4
Classifier: Topic :: Internet :: WWW/HTTP
Classifier: Topic :: Internet :: WWW/HTTP :: Dynamic Content
Requires-Dist: wheel (==0.24.0)
Requires-Dist: xerox (==0.4.1)
